mkfpdf/__init__.py
mkfpdf/pdf2image.py
mkfpdf/pdf2text.py
mkfpdf-1.0.1.dist-info/licenses/LICENSE
mkfpdf-1.0.1.dist-info/METADATA
mkfpdf-1.0.1.dist-info/WHEEL
mkfpdf-1.0.1.dist-info/top_level.txt
mkfpdf-1.0.1.dist-info/RECORD
