Metadata-Version: 2.4
Name: mkfpdf
Version: 1.0.1
License-File: LICENSE
Dynamic: description
Dynamic: description-content-type
Dynamic: license-file
